lendsmart_api/__init__.py
lendsmart_api/common.py
lendsmart_api/constants.py
lendsmart_api/errors.py
lendsmart_api/lendsmart_client.py
lendsmart_api/paginated_list.py
lendsmart_api/jwt/__init__.py
lendsmart_api/jwt/compat.py
lendsmart_api/jwt/access_token/__init__.py
lendsmart_api/jwt/access_token/service_account.py
lendsmart_api/objects/__init__.py
lendsmart_api/objects/account.py
lendsmart_api/objects/advisors.py
lendsmart_api/objects/base.py
lendsmart_api/objects/dbase.py
lendsmart_api/objects/document.py
lendsmart_api/objects/document_pointer.py
lendsmart_api/objects/filtering.py
lendsmart_api/objects/finicity.py
lendsmart_api/objects/lending_term.py
lendsmart_api/objects/letter_of_explanations.py
lendsmart_api/objects/namespace.py
lendsmart_api/objects/notifier.py
lendsmart_api/objects/openids.py
lendsmart_api/objects/prediction.py
lendsmart_api/objects/signature.py
lendsmart_api/objects/task.py
test/__init__.py
test/advisor_profiles_test.py
test/base.py
test/fixtures.py
test/freddie_mac_test.py
test/lendsmart_client_test.py
test/letter_of_explanations_test.py
test/loan_status_test.py
test/openid_test.py
test/originating_loan_permission_test.py
test/task_test.py
test/team_member_test.py
test/objects/__init__.py
test/objects/document_test.py
test/objects/prediction_test.py
test/objects/test_access_token.py
lendsmart_api-2.14.dist-info/LICENSE
lendsmart_api-2.14.dist-info/METADATA
lendsmart_api-2.14.dist-info/WHEEL
lendsmart_api-2.14.dist-info/top_level.txt
lendsmart_api-2.14.dist-info/RECORD
