Metadata-Version: 2.1
Name: lendsmart-api
Version: 2.14
Summary: The official python SDK for LendSmart API v1
Home-page: https://github.com/lendsmartlabs/py_lsclient/
Author: Smart Labs
Author-email: infos@lendsmart.ai
License: MIT
Keywords: prediction ai lendsmart
Classifier: Development Status :: 3 - Alpha
Classifier: Intended Audience :: Developers
Classifier: Topic :: Software Development :: Libraries
Classifier: License :: OSI Approved :: MIT License
Classifier: Programming Language :: Python
Classifier: Programming Language :: Python :: 3.7
Classifier: Programming Language :: Python :: 3.8
Classifier: Programming Language :: Python :: 3.9
License-File: LICENSE
Requires-Dist: future
Requires-Dist: requests
Requires-Dist: retry
